creatediscordbot/__init__.py
creatediscordbot/discordbot.py
creatediscordbot/templater.py
creatediscordbot/utils.py
creatediscordbot/bot_template/.env
creatediscordbot/bot_template/.env.debug
creatediscordbot/bot_template/.gitignore
creatediscordbot/bot_template/__init__.py
creatediscordbot/bot_template/logger.prod.yml
creatediscordbot/bot_template/logger.yml
creatediscordbot/bot_template/main.py
creatediscordbot/bot_template/requirements.txt
creatediscordbot/bot_template/settings.py
creatediscordbot/bot_template/cogs/__init__.py
creatediscordbot/bot_template/cogs/admin/__init__.py
creatediscordbot/bot_template/cogs/admin/admin.py
creatediscordbot/bot_template/cogs/admin/controller.py
creatediscordbot/bot_template/cogs/admin/converter.py
creatediscordbot/bot_template/cogs/admin/model.py
creatediscordbot/bot_template/cogs/admin/tests/__init__.py
creatediscordbot/bot_template/cogs/admin/tests/test_controller.py
creatediscordbot/bot_template/cogs/admin/tests/test_converter.py
creatediscordbot/bot_template/cogs/admin/tests/test_model.py
creatediscordbot/bot_template/settings_files/__init__.py
creatediscordbot/bot_template/settings_files/_global.py
creatediscordbot/bot_template/settings_files/development.py
creatediscordbot/bot_template/settings_files/production.py
creatediscordbot/bot_template/uncategorised_commands/__init__.py
creatediscordbot/bot_template/uncategorised_commands/command.py-temp
creatediscordbot/bot_template/uncategorised_commands/loader.py
creatediscordbot/cog_template/__init__.py
creatediscordbot/cog_template/cog_bare.py-temp
creatediscordbot/cog_template/cog_full.py-temp
creatediscordbot/cog_template/controller.py-temp
creatediscordbot/cog_template/converter.py
creatediscordbot/cog_template/model.py
creatediscordbot/cog_template/tests/__init__.py
creatediscordbot/cog_template/tests/test_controller.py
creatediscordbot/cog_template/tests/test_converter.py
creatediscordbot/cog_template/tests/test_model.py
create_discord_bot-0.10.dist-info/LICENSE
create_discord_bot-0.10.dist-info/METADATA
create_discord_bot-0.10.dist-info/WHEEL
create_discord_bot-0.10.dist-info/entry_points.txt
create_discord_bot-0.10.dist-info/top_level.txt
create_discord_bot-0.10.dist-info/RECORD
