Metadata-Version: 2.1
Name: create-discord-bot
Version: 0.10
Summary: Simply create a new discordpy discord bot with a predefined structure and helpers to create Cogs, Commands or dockerizing the project
Home-page: https://github.com/StartupTechTutorial/create-discord-bot
Author: StartupTechTutorials
Author-email: hello@startuptechtutorials.com
License: GNU 3.0
Platform: UNKNOWN
Requires-Python: >=3.6, <4
Requires-Dist: colorama (>=0.4.3)
